cache/__init__.py
cache/__main__.py
cache/cli.py
cache/client/__init__.py
cache/client/python/__init__.py
cache/client/python/client.py
cache/core/__init__.py
cache/core/doublylinkedlist.py
cache/core/tests/__init__.py
cache/core/tests/test_doublylinkedlist.py
cache/gen/__init__.py
cache/gen/keyvalue/KeyValueService.py
cache/gen/keyvalue/__init__.py
cache/gen/keyvalue/constants.py
cache/gen/keyvalue/ttypes.py
cache/server/__init__.py
cache/server/cachehandler.py
cache/server/server.py
cache/server/tests/__init__.py
cache/server/tests/test_cachehandler.py
thriftcacheserver-1.5.dist-info/LICENSE
thriftcacheserver-1.5.dist-info/METADATA
thriftcacheserver-1.5.dist-info/WHEEL
thriftcacheserver-1.5.dist-info/entry_points.txt
thriftcacheserver-1.5.dist-info/top_level.txt
thriftcacheserver-1.5.dist-info/RECORD
